{
	"id": "sony-fx6--20mm--3840x2160",
	"camera_brand": "Sony",
	"camera_model": "FX6",
	"lens_model": "Canon FDn 20mm f2.8",
	"resolution": {
		"width": 3840,
		"height": 2160
	},
	"distortion_model": "fisheye_kb4",
	"camera_matrix": {
		"fx": 2249.2428426139427,
		"fy": 2248.574985091623,
		"cx": 1923.3584229202936,
		"cy": 1060.7271573356825
	},
	"distortion_coeffs": [
		0.2299943084760646,
		0.1961769194174548,
		-0.11008377754725564,
		0.2891087697756602
	],
	"metadata": {
		"calibrated_by": "Holgerson",
		"notes": "20mm",
		"source": "gyroflow",
		"official": true
	}
}