{
	"id": "blackmagic-pocket-cinema-camera-4k-laowa-17mm-f18-3840x2160",
	"camera_brand": "Blackmagic",
	"camera_model": "Pocket Cinema Camera 4k",
	"lens_model": "Laowa 17mm f1.8",
	"resolution": {
		"width": 3840,
		"height": 2160
	},
	"distortion_model": "fisheye_kb4",
	"camera_matrix": {
		"fx": 3774.8945904468064,
		"fy": 3771.86843249512,
		"cx": 1922.5785095116523,
		"cy": 1072.0024032556812
	},
	"distortion_coeffs": [
		0.201101251614332,
		0.08124820683195526,
		3.246536089890954,
		-14.345835752996036
	],
	"metadata": {
		"source": "Gyroflow lens_profiles",
		"source_file": "Blackmagic_Pocket Cinema Camera 4k_Laowa 17mm f1.8__4k_16by9_3840x2160-24.00fps",
		"calibrated_by": "Justin Kramer",
		"original_resolution": "3840x2160",
		"calibrated_fps": "24.0",
		"official": false,
		"notes": "Gyroflow calibration. Fisheye distortion model.",
		"license": "CC0 1.0 Universal"
	}
}