{
	"id": "red-komodo-laowa-75-5760x3240",
	"camera_brand": "RED",
	"camera_model": "KOMODO",
	"lens_model": "Laowa 7.5",
	"resolution": {
		"width": 5760,
		"height": 3240
	},
	"distortion_model": "fisheye_kb4",
	"camera_matrix": {
		"fx": 1778.079032656573,
		"fy": 1778.0969236961869,
		"cx": 2872.1891142532636,
		"cy": 1627.063683075692
	},
	"distortion_coeffs": [
		0.3207378126955032,
		0.20354460975453395,
		-0.0863967927867444,
		0.10403418955484338
	],
	"metadata": {
		"source": "Gyroflow lens_profiles",
		"source_file": "RED_KOMODO_Laowa 7.5_6K 17:9_5k_16by9_5760x3240-25.00fps",
		"calibrated_by": "ILL Camaras",
		"original_resolution": "5760x3240",
		"calibrated_fps": "25.0",
		"official": false,
		"notes": "Gyroflow calibration. Fisheye distortion model.",
		"license": "CC0 1.0 Universal"
	}
}