{
	"id": "sony-fx3-9000mm-g-macro-3840x2160",
	"camera_brand": "Sony",
	"camera_model": "FX3",
	"lens_model": "90.00mm G Macro",
	"resolution": {
		"width": 3840,
		"height": 2160
	},
	"distortion_model": "fisheye_kb4",
	"camera_matrix": {
		"fx": 10125.993550554122,
		"fy": 10144.622858498851,
		"cx": 1780.5737537060447,
		"cy": 891.9561888991051
	},
	"distortion_coeffs": [
		0.16916008905404786,
		-0.3365635642462575,
		8.093951038315339,
		-99.11477490631816
	],
	"metadata": {
		"source": "Gyroflow lens_profiles",
		"source_file": "Sony_FX3_90.00mm G Macro__4k_16by9_3840x2160-23.98fps",
		"calibrated_by": "Pabby",
		"original_resolution": "3840x2160",
		"calibrated_fps": "23.976025",
		"official": false,
		"notes": "Gyroflow calibration. Fisheye distortion model.",
		"license": "CC0 1.0 Universal"
	}
}