{
	"id": "insta360-oners-ultrawide-110-5312x2988",
	"camera_brand": "Insta360",
	"camera_model": "OneRS",
	"lens_model": "Ultrawide 110",
	"resolution": {
		"width": 5312,
		"height": 2988
	},
	"distortion_model": "fisheye_kb4",
	"camera_matrix": {
		"fx": 2204.3251140577595,
		"fy": 2204.121855032201,
		"cx": 2715.437994806211,
		"cy": 1576.4443885874537
	},
	"distortion_coeffs": [
		0.06002591073214594,
		-0.0058551191028717725,
		0.011746041969209049,
		-0.00829050496572599
	],
	"metadata": {
		"source": "Gyroflow lens_profiles",
		"source_file": "Insta360_OneRS_Ultrawide 110_NO-EIS_5k_16by9_5312x2988-25.00fps",
		"calibrated_by": "MacPro",
		"original_resolution": "5312x2988",
		"calibrated_fps": "25.0",
		"official": false,
		"notes": "Gyroflow calibration. Fisheye distortion model.",
		"license": "CC0 1.0 Universal"
	}
}