{
	"id": "insta360-oners-ultrawide-110-4352x2448",
	"camera_brand": "Insta360",
	"camera_model": "OneRS",
	"lens_model": "Ultrawide 110",
	"resolution": {
		"width": 4352,
		"height": 2448
	},
	"distortion_model": "fisheye_kb4",
	"camera_matrix": {
		"fx": 2102.736295911404,
		"fy": 2105.2041198919533,
		"cx": 2204.9445410569924,
		"cy": 1284.259929836428
	},
	"distortion_coeffs": [
		-0.023095565461211557,
		-0.07751267322732952,
		0.17878235945530055,
		-0.11289576525982711
	],
	"metadata": {
		"source": "Gyroflow lens_profiles",
		"source_file": "Insta360_OneRS_Ultrawide 110_1 inch Leica_C4k_16by9_4352x2448-29.97fps",
		"calibrated_by": "4FM EZ",
		"original_resolution": "4352x2448",
		"calibrated_fps": "29.97003",
		"official": false,
		"notes": "Gyroflow calibration. Fisheye distortion model.",
		"license": "CC0 1.0 Universal"
	}
}