{
	"id": "z-cam-e2-m4--c4k--4096x2160",
	"camera_brand": "Z-Cam",
	"camera_model": "E2-M4",
	"lens_model": "Laowa 7.5mm",
	"resolution": {
		"width": 4096,
		"height": 2160
	},
	"distortion_model": "fisheye_kb4",
	"camera_matrix": {
		"fx": 1661.9322261176706,
		"fy": 1662.2145976789243,
		"cx": 2056.901460756359,
		"cy": 1062.0975555204204
	},
	"distortion_coeffs": [
		0.3257516451003388,
		0.1287458361916268,
		-0.04330130196073896,
		0.0967382887131097
	],
	"metadata": {
		"calibrated_by": "Captain Kangaroo",
		"notes": "C4K",
		"source": "gyroflow",
		"official": true
	}
}