{
	"id": "red-komodo-6k-meike-25mm-t22-4096x2160",
	"camera_brand": "RED",
	"camera_model": "KOMODO 6K",
	"lens_model": "Meike 25mm T2.2",
	"resolution": {
		"width": 4096,
		"height": 2160
	},
	"distortion_model": "fisheye_kb4",
	"camera_matrix": {
		"fx": 3803.902262596427,
		"fy": 3802.651716203276,
		"cx": 2042.8973036272291,
		"cy": 1068.3871949724498
	},
	"distortion_coeffs": [
		0.24435821720353695,
		0.23862952630717785,
		-0.42278577995727745,
		1.5607277181581791
	],
	"metadata": {
		"source": "Gyroflow lens_profiles",
		"source_file": "RED_KOMODO 6K_Meike 25mm T2.2_6K 17:9_C4k_1.90by1_4096x2160-23.98fps",
		"calibrated_by": "Vortex Aerial",
		"original_resolution": "4096x2160",
		"calibrated_fps": "23.976025",
		"official": false,
		"notes": "Gyroflow calibration. Fisheye distortion model.",
		"license": "CC0 1.0 Universal"
	}
}