{
	"id": "red-komodo-6k-nikkor-18mm-vintage-6144x3240",
	"camera_brand": "RED",
	"camera_model": "KOMODO 6K",
	"lens_model": "NIKKOR 18MM VINTAGE",
	"resolution": {
		"width": 6144,
		"height": 3240
	},
	"distortion_model": "fisheye_kb4",
	"camera_matrix": {
		"fx": 4269.678636141894,
		"fy": 4267.0309286697175,
		"cx": 3094.3552214742476,
		"cy": 1617.919816439883
	},
	"distortion_coeffs": [
		0.26270406492317616,
		-0.18197349257492765,
		1.0984706380271314,
		-1.007291040782796
	],
	"metadata": {
		"source": "Gyroflow lens_profiles",
		"source_file": "RED_KOMODO 6K_NIKKOR 18MM VINTAGE_6K 17:9_6k_1.90by1_6144x3240-23.98fps",
		"calibrated_by": "Joey Killeen",
		"original_resolution": "6144x3240",
		"calibrated_fps": "23.976025",
		"official": false,
		"notes": "Gyroflow calibration. Fisheye distortion model.",
		"license": "CC0 1.0 Universal"
	}
}