{
	"id": "red-komodo-6k-laowa-75mm-t29-cine-lens-6144x3240",
	"camera_brand": "RED",
	"camera_model": "KOMODO 6K",
	"lens_model": "Laowa 7.5mm T/2.9 Cine Lens",
	"resolution": {
		"width": 6144,
		"height": 3240
	},
	"distortion_model": "fisheye_kb4",
	"camera_matrix": {
		"fx": 1769.090047243619,
		"fy": 1769.7434816631358,
		"cx": 3086.9726460506195,
		"cy": 1619.2736100373916
	},
	"distortion_coeffs": [
		0.3150740895765315,
		0.2095375694982492,
		-0.09692366084541708,
		0.1026573429179321
	],
	"metadata": {
		"source": "Gyroflow lens_profiles",
		"source_file": "RED_KOMODO 6K_Laowa 7.5mm T/2.9 Cine Lens_6K 17:9_6k_1.90by1_6144x3240-25.00fps",
		"calibrated_by": "Benjam\u00edn Heimisson",
		"original_resolution": "6144x3240",
		"calibrated_fps": "25.0",
		"official": false,
		"notes": "Gyroflow calibration. Fisheye distortion model.",
		"license": "CC0 1.0 Universal"
	}
}