{
	"id": "sony-fx30-viltrox-2300mm-3840x2160",
	"camera_brand": "Sony",
	"camera_model": "FX30",
	"lens_model": "Viltrox 23.00mm",
	"resolution": {
		"width": 3840,
		"height": 2160
	},
	"distortion_model": "fisheye_kb4",
	"camera_matrix": {
		"fx": 4225.899094395034,
		"fy": 4228.023110227249,
		"cx": 1955.3517704847652,
		"cy": 1068.0926817350676
	},
	"distortion_coeffs": [
		0.1988380584364536,
		-0.09493376371780192,
		2.1310019757909906,
		-2.239984095667274
	],
	"metadata": {
		"source": "Gyroflow lens_profiles",
		"source_file": "Sony_FX30_Viltrox 23.00mm__4k_16by9_3840x2160-29.97fps",
		"calibrated_by": "Lukas",
		"original_resolution": "3840x2160",
		"calibrated_fps": "29.97003",
		"official": false,
		"notes": "Gyroflow calibration. Fisheye distortion model.",
		"license": "CC0 1.0 Universal"
	}
}