{
	"id": "blackmagic-pocket-cinema-camera-6k-dzofilm-35mm-t21-6144x3456",
	"camera_brand": "Blackmagic",
	"camera_model": "Pocket Cinema Camera 6k",
	"lens_model": "DZOFILM 35mm T2.1",
	"resolution": {
		"width": 6144,
		"height": 3456
	},
	"distortion_model": "fisheye_kb4",
	"camera_matrix": {
		"fx": 9067.10075187364,
		"fy": 9067.42110037204,
		"cx": 3206.474451255647,
		"cy": 1844.4091111441492
	},
	"distortion_coeffs": [
		0.19864455352150123,
		-0.20948139613874223,
		3.675774663434993,
		-8.644196951522854
	],
	"metadata": {
		"source": "Gyroflow lens_profiles",
		"source_file": "Blackmagic_Pocket Cinema Camera 6k_DZOFILM 35mm T2.1_RAW 12:1_6k_16by9_6144x3456-50.00fps",
		"calibrated_by": "\u5c1a\u6587",
		"original_resolution": "6144x3456",
		"calibrated_fps": "50.0",
		"official": false,
		"notes": "Gyroflow calibration. Fisheye distortion model.",
		"license": "CC0 1.0 Universal"
	}
}